Typeform/__init__.py
TypeformETL/__init__.py
TypeformETL/__main__.py
TypeformETL-0.6.2.data/data/share/TypeformETL/examples/NPS Analysis.ipynb
TypeformETL-0.6.2.data/data/share/TypeformETL/examples/datamodel.sql
TypeformETL-0.6.2.data/data/share/TypeformETL/examples/syncFromTypeform.conf.example
TypeformETL-0.6.2.dist-info/LICENSE
TypeformETL-0.6.2.dist-info/METADATA
TypeformETL-0.6.2.dist-info/WHEEL
TypeformETL-0.6.2.dist-info/top_level.txt
TypeformETL-0.6.2.dist-info/RECORD
