Metadata-Version: 2.1
Name: TypeformETL
Version: 0.6.2
Summary: Ingest all data from a Typeform account and put the data into a SQL database; can be run regularly to sync updates to DB
Home-page: https://github.com/avibrazil/Typeform-ETL
Author: Avi Alkalay
Author-email: avibrazil@gmail.com
License: UNKNOWN
Platform: UNKNOWN
Classifier: Programming Language :: Python :: 3
Classifier: Operating System :: OS Independent
Classifier: Development Status :: 4 - Beta
Classifier: Environment :: Console
Classifier: Intended Audience :: Developers
Classifier: Intended Audience :: End Users/Desktop
Classifier: Intended Audience :: Information Technology
Classifier: License :: OSI Approved :: GNU Library or Lesser General Public License (LGPL)
Classifier: Operating System :: POSIX
Classifier: Topic :: Database
Classifier: Topic :: Software Development :: Libraries :: Python Modules
Classifier: Topic :: Internet
Requires-Python: >=3.6
Requires-Dist: sqlalchemy
Requires-Dist: pandas
Requires-Dist: requests
Requires-Dist: configobj
